ctxkit/__init__.py
ctxkit/__main__.py
ctxkit/claude.py
ctxkit/gemini.py
ctxkit/gpt.py
ctxkit/grok.py
ctxkit/main.py
ctxkit/ollama.py
ctxkit-2.1.0.dist-info/licenses/LICENSE
ctxkit-2.1.0.dist-info/METADATA
ctxkit-2.1.0.dist-info/WHEEL
ctxkit-2.1.0.dist-info/entry_points.txt
ctxkit-2.1.0.dist-info/top_level.txt
ctxkit-2.1.0.dist-info/RECORD
