Metadata-Version: 2.4
Name: ctxkit
Version: 2.1.0
Summary: ctxkit is a command-line tool for creating AI prompts to modify code.
Home-page: https://github.com/craigahobbs/ctxkit
Author: Craig A. Hobbs
Author-email: craigahobbs@gmail.com
License: MIT
Keywords: ctxkit
Classifier: Development Status :: 5 - Production/Stable
Classifier: Intended Audience :: Developers
Classifier: Operating System :: OS Independent
Classifier: Programming Language :: Python :: 3.10
Classifier: Programming Language :: Python :: 3.11
Classifier: Programming Language :: Python :: 3.12
Classifier: Programming Language :: Python :: 3.13
Classifier: Programming Language :: Python :: 3.14
Classifier: Topic :: Utilities
License-File: LICENSE
Requires-Dist: schema-markdown>=1.2.0
Requires-Dist: urllib3>=2.5.0
Dynamic: license-file
